agirails/__init__.py
agirails/client.py
agirails/py.typed
agirails/version.py
agirails/abi/ACTPKernel.json
agirails/abi/ERC20.json
agirails/abi/EscrowVault.json
agirails/abis/actp_kernel.json
agirails/abis/agent_registry.json
agirails/abis/eas.json
agirails/abis/escrow_vault.json
agirails/abis/usdc.json
agirails/adapters/__init__.py
agirails/adapters/base.py
agirails/adapters/basic.py
agirails/adapters/standard.py
agirails/builders/__init__.py
agirails/builders/delivery_proof.py
agirails/builders/quote.py
agirails/cli/__init__.py
agirails/cli/main.py
agirails/cli/commands/__init__.py
agirails/cli/commands/balance.py
agirails/cli/commands/batch.py
agirails/cli/commands/config.py
agirails/cli/commands/init.py
agirails/cli/commands/mint.py
agirails/cli/commands/pay.py
agirails/cli/commands/simulate.py
agirails/cli/commands/time.py
agirails/cli/commands/tx.py
agirails/cli/commands/watch.py
agirails/cli/utils/__init__.py
agirails/cli/utils/client.py
agirails/cli/utils/output.py
agirails/cli/utils/validation.py
agirails/config/__init__.py
agirails/config/networks.py
agirails/config/abis/AgentRegistry.json
agirails/errors/__init__.py
agirails/errors/agent.py
agirails/errors/base.py
agirails/errors/mock.py
agirails/errors/network.py
agirails/errors/storage.py
agirails/errors/transaction.py
agirails/errors/validation.py
agirails/level0/__init__.py
agirails/level0/directory.py
agirails/level0/provide.py
agirails/level0/provider.py
agirails/level0/request.py
agirails/level1/__init__.py
agirails/level1/agent.py
agirails/level1/config.py
agirails/level1/job.py
agirails/level1/pricing.py
agirails/protocol/__init__.py
agirails/protocol/agent_registry.py
agirails/protocol/did.py
agirails/protocol/eas.py
agirails/protocol/escrow.py
agirails/protocol/events.py
agirails/protocol/kernel.py
agirails/protocol/messages.py
agirails/protocol/nonce.py
agirails/protocol/proofs.py
agirails/runtime/__init__.py
agirails/runtime/base.py
agirails/runtime/blockchain_runtime.py
agirails-2.0.0.dist-info/METADATA
agirails-2.0.0.dist-info/WHEEL
agirails-2.0.0.dist-info/entry_points.txt
agirails-2.0.0.dist-info/licenses/LICENSE
agirails-2.0.0.dist-info/RECORD
