Metadata-Version: 2.4
Name: agirails
Version: 2.0.0
Summary: AGIRAILS Python SDK - Agent Commerce Transaction Protocol
Project-URL: Homepage, https://agirails.io
Project-URL: Documentation, https://docs.agirails.io
Project-URL: Repository, https://github.com/agirails/sdk-python
Project-URL: Issues, https://github.com/agirails/sdk-python/issues
Author-email: AGIRAILS Team <developers@agirails.io>
License-Expression: Apache-2.0
License-File: LICENSE
Keywords: actp,ai-agents,base,blockchain,escrow,ethereum,payments,web3
Classifier: Development Status :: 4 - Beta
Classifier: Intended Audience :: Developers
Classifier: License :: OSI Approved :: Apache Software License
Classifier: Operating System :: OS Independent
Classifier: Programming Language :: Python :: 3
Classifier: Programming Language :: Python :: 3.9
Classifier: Programming Language :: Python :: 3.10
Classifier: Programming Language :: Python :: 3.11
Classifier: Programming Language :: Python :: 3.12
Classifier: Topic :: Software Development :: Libraries :: Python Modules
Classifier: Typing :: Typed
Requires-Python: >=3.9
Requires-Dist: aiofiles<25.0.0,>=24.0.0
Requires-Dist: eth-abi<6.0.0,>=5.0.0
Requires-Dist: eth-account<0.14.0,>=0.13.0
Requires-Dist: httpx<1.0.0,>=0.27.0
Requires-Dist: pydantic<3.0.0,>=2.6.0
Requires-Dist: python-dateutil<3.0.0,>=2.8.0
Requires-Dist: rich<14.0.0,>=13.0.0
Requires-Dist: typer<1.0.0,>=0.12.0
Requires-Dist: typing-extensions<5.0.0,>=4.0.0; python_version < '3.10'
Requires-Dist: web3<8.0.0,>=7.0.0
Provides-Extra: dev
Requires-Dist: black>=24.0.0; extra == 'dev'
Requires-Dist: hypothesis>=6.100.0; extra == 'dev'
Requires-Dist: mypy>=1.11.0; extra == 'dev'
Requires-Dist: pytest-asyncio>=0.24.0; extra == 'dev'
Requires-Dist: pytest-benchmark>=4.0.0; extra == 'dev'
Requires-Dist: pytest-cov>=5.0.0; extra == 'dev'
Requires-Dist: pytest-timeout>=2.3.0; extra == 'dev'
Requires-Dist: pytest-xdist>=3.5.0; extra == 'dev'
Requires-Dist: pytest>=8.0.0; extra == 'dev'
Requires-Dist: ruff>=0.6.0; extra == 'dev'
Requires-Dist: types-aiofiles>=24.0.0; extra == 'dev'
Requires-Dist: types-python-dateutil>=2.8.0; extra == 'dev'
Provides-Extra: mutation
Requires-Dist: mutmut>=2.4.0; extra == 'mutation'
Provides-Extra: security
Requires-Dist: bandit>=1.7.0; extra == 'security'
Requires-Dist: pip-audit>=2.7.0; extra == 'security'
Requires-Dist: safety>=3.0.0; extra == 'security'
